gps/__init__.py
gps/chromatograms.py
gps/combiner.py
gps/denoiser.py
gps/fdr.py
gps/peakgroups.py
gps/peptides.py
gps/precursors.py
gps/preprocess.py
gps/proteins.py
gps/scaler.py
gps/scorer.py
gps/cli/__init__.py
gps/cli/build.py
gps/cli/combine.py
gps/cli/createlib.py
gps/cli/denoise.py
gps/cli/export.py
gps/cli/gps
gps/cli/predict.py
gps/cli/score.py
gps/cli/train.py
gps/models/__init__.py
gps/models/base_model.py
gps/models/deep_chromatogram_classifier.py
gps/models/trained/__init__.py
gps/models/trained/scoring.model
gps/models/trained/scoring.scaler
gps/parsers/__init__.py
gps/parsers/osw.py
gps/parsers/pqp_file.py
gps/parsers/queries.py
gps/parsers/score_file.py
gps/parsers/sqlite_file.py
gps/parsers/sqmass.py
gps_ms-0.0.1.data/scripts/gps
gps_ms-0.0.1.dist-info/LICENSE
gps_ms-0.0.1.dist-info/METADATA
gps_ms-0.0.1.dist-info/WHEEL
gps_ms-0.0.1.dist-info/top_level.txt
gps_ms-0.0.1.dist-info/RECORD
