Metadata-Version: 2.1
Name: gps-ms
Version: 0.0.1
Summary: A self-denoising and machine-learning based statistical generalized peakgroup scoring algorithm for SWATH-MS data
Author: Aaron Scott
Author-email: Aaron Scott <aaron.scott@med.lu.se>
Project-URL: Homepage, https://github.com/InfectionMedicineProteomics/gps
Project-URL: Bug Tracker, https://github.com/InfectionMedicineProteomics/gps/issues
Classifier: Programming Language :: Python :: 3
Classifier: License :: OSI Approved :: MIT License
Classifier: Operating System :: OS Independent
Requires-Python: >=3.7
License-File: LICENSE
Requires-Dist: sklearn
Requires-Dist: numpy
Requires-Dist: numba
Requires-Dist: torch
Requires-Dist: pytorch-lightning
Requires-Dist: torchvision
Requires-Dist: imblearn
Requires-Dist: xgboost (==1.5.0)
